Docker_Compose_Templer-1.1.0.post2.data/scripts/docker-compose-templer
docker_compose_templer/__init__.py
docker_compose_templer/auto_renderer.py
docker_compose_templer/cached_file.py
docker_compose_templer/context.py
docker_compose_templer/definition.py
docker_compose_templer/event.py
docker_compose_templer/jinja_filter.py
docker_compose_templer/jinja_renderer.py
docker_compose_templer/log.py
docker_compose_templer/template.py
docker_compose_templer/utils.py
Docker_Compose_Templer-1.1.0.post2.dist-info/LICENSE.txt
Docker_Compose_Templer-1.1.0.post2.dist-info/METADATA
Docker_Compose_Templer-1.1.0.post2.dist-info/WHEEL
Docker_Compose_Templer-1.1.0.post2.dist-info/top_level.txt
Docker_Compose_Templer-1.1.0.post2.dist-info/RECORD
