Metadata-Version: 2.1
Name: Docker-Compose-Templer
Version: 1.1.0.post2
Summary: Render Docker Compose file templates with the power of Jinja2
Home-page: https://github.com/Aisbergg/python-docker-compose-templer
Author: Andre Lehmann
Author-email: aisberg@posteo.de
License: LGPL
Project-URL: Bug Reports, https://github.com/Aisbergg/python-docker-compose-templer/issues
Project-URL: Source, https://github.com/Aisbergg/python-docker-compose-templer
Keywords: Jinja2 templating command-line CLI "Docker-Compose"
Platform: POSIX
Classifier: Development Status :: 4 - Beta
Classifier: Environment :: Console
Classifier: Intended Audience :: Developers
Classifier: Intended Audience :: System Administrators
Classifier: License :: OSI Approved :: GNU Lesser General Public License v3 (LGPLv3)
Classifier: Operating System :: POSIX
Classifier: Programming Language :: Python :: 3 :: Only
Classifier: Topic :: System :: Systems Administration
Classifier: Topic :: Utilities
Requires-Dist: jinja2
Requires-Dist: ruamel.yaml
Provides-Extra: autorenderer
Requires-Dist: pyinotify ; extra == 'autorenderer'
